fake_gradio/__init__.py
void_terminal/Dockerfile
void_terminal/LICENSE
void_terminal/README.md
void_terminal/__init__.py
void_terminal/check_proxy.py
void_terminal/config.py
void_terminal/core_functional.py
void_terminal/crazy_functional.py
void_terminal/docker-compose.yml
void_terminal/main.py
void_terminal/requirements.txt
void_terminal/toolbox.py
void_terminal/version
void_terminal/crazy_functions/Accessibility.py
void_terminal/crazy_functions/AdvancedFunctionTemplate.py
void_terminal/crazy_functions/BatchSummarizePDFDocuments.py
void_terminal/crazy_functions/BatchSummarizePDFDocumentsUsingPdfminer.py
void_terminal/crazy_functions/BatchTranslatePDFDocuments_NOUGAT.py
void_terminal/crazy_functions/ChatGLMFineTuningTool.py
void_terminal/crazy_functions/ChatGPTConnectedToNetwork.py
void_terminal/crazy_functions/Conversation_To_File.py
void_terminal/crazy_functions/DownloadArxivPaperTranslateAbstract.py
void_terminal/crazy_functions/DynamicFunctionGeneration.py
void_terminal/crazy_functions/FullTextProofreadingForLatex.py
void_terminal/crazy_functions/GenerateFunctionComments.py
void_terminal/crazy_functions/GenerateMultipleMermaidCharts.py
void_terminal/crazy_functions/GoogleSearchAssistant.py
void_terminal/crazy_functions/Image_Generate.py
void_terminal/crazy_functions/Image_Generate_Wrap.py
void_terminal/crazy_functions/InquiryMultipleLargeLanguageModels.py
void_terminal/crazy_functions/InteractiveFunctionFunctionTemplate.py
void_terminal/crazy_functions/InteractiveMiniGame.py
void_terminal/crazy_functions/Internet_GPT.py
void_terminal/crazy_functions/Internet_GPT_Wrap.py
void_terminal/crazy_functions/LatexFullTextTranslation.py
void_terminal/crazy_functions/Latex_Function.py
void_terminal/crazy_functions/Latex_Function_Wrap.py
void_terminal/crazy_functions/Markdown_Translate.py
void_terminal/crazy_functions/MathematicalAnimationGenerationManim.py
void_terminal/crazy_functions/MultiAgent.py
void_terminal/crazy_functions/OnlineChatGPT_BingEdition.py
void_terminal-1.1.2.dist-info/METADATA
void_terminal-1.1.2.dist-info/WHEEL
void_terminal-1.1.2.dist-info/dependency_links.txt
void_terminal-1.1.2.dist-info/entry_points.txt
void_terminal-1.1.2.dist-info/top_level.txt
void_terminal-1.1.2.dist-info/RECORD
