Metadata-Version: 2.1
Name: void-terminal
Version: 1.1.2
Summary: LLM based APIs
Home-page: https://github.com/binary-husky/void-terminal
Author: Qingxu
Author-email: 505030475@qq.com
Project-URL: Bug Tracker, https://github.com/binary-husky/void-terminal/issues
Classifier: Programming Language :: Python :: 3
Classifier: License :: OSI Approved :: MIT License
Classifier: Operating System :: OS Independent
Requires-Python: >=3.8
Requires-Dist: fastapi (==0.110)
Requires-Dist: gradio-client (==0.8)
Requires-Dist: pypdf2 (==2.12.1)
Requires-Dist: zhipuai (==2.0.1)
Requires-Dist: tiktoken (>=0.3.3)
Requires-Dist: requests[socks]
Requires-Dist: pydantic
Requires-Dist: llama-index (~=0.10)
Requires-Dist: protobuf (==3.20)
Requires-Dist: transformers (<4.42,>=4.27.1)
Requires-Dist: scipdf-parser (>=0.52)
Requires-Dist: anthropic (>=0.18.1)
Requires-Dist: python-markdown-math
Requires-Dist: pymdown-extensions
Requires-Dist: websocket-client
Requires-Dist: beautifulsoup4
Requires-Dist: prompt-toolkit
Requires-Dist: latex2mathml
Requires-Dist: python-docx
Requires-Dist: mdtex2html
Requires-Dist: dashscope
Requires-Dist: pyautogen
Requires-Dist: colorama
Requires-Dist: Markdown
Requires-Dist: pygments
Requires-Dist: edge-tts
Requires-Dist: pymupdf
Requires-Dist: openai
Requires-Dist: rjsmin
Requires-Dist: loguru
Requires-Dist: arxiv
Requires-Dist: numpy
Requires-Dist: rich
